promptsapi/__init__.py
promptsapi/client.py
promptsapi-0.2.0.dist-info/METADATA
promptsapi-0.2.0.dist-info/WHEEL
promptsapi-0.2.0.dist-info/top_level.txt
promptsapi-0.2.0.dist-info/RECORD
