Metadata-Version: 2.4
Name: promptsapi
Version: 0.2.0
Summary: A client library for the prompts-testing API.
Author-email: simpaisush <info@promptsgenerator.ai>
Project-URL: Homepage, https://github.com/your-github-username/promptsapi
Project-URL: Bug Tracker, https://github.com/your-github-username/promptsapi/issues
Classifier: Programming Language :: Python :: 3
Classifier: License :: OSI Approved :: MIT License
Classifier: Operating System :: OS Independent
Requires-Python: >=3.7
Requires-Dist: requests>=2.25.1
